Calculator_Hao/Calculator.py
Calculator_Hao/__init__.py
Calculator_Hao-0.0.2.dist-info/LICENSE
Calculator_Hao-0.0.2.dist-info/METADATA
Calculator_Hao-0.0.2.dist-info/WHEEL
Calculator_Hao-0.0.2.dist-info/top_level.txt
Calculator_Hao-0.0.2.dist-info/RECORD
