Metadata-Version: 2.1
Name: Calculator-Hao
Version: 0.0.2
Summary: This is a very basic calculator
Home-page: UNKNOWN
Author: Hao LI
Author-email: olivierlihao@gmail.com
License: UNKNOWN
Platform: UNKNOWN
Classifier: Development Status :: 1 - Planning
Classifier: Programming Language :: Python :: 3
